<?xml version="1.0" encoding="utf-8" ?>
<dwsync>
<file name="ralc_banner_bkg.png" server="Y:/" local="128866283220000000" remote="128866283220000000" Dst="2" />
<file name="ralc_logo.png" server="Y:/" local="128866284120000000" remote="128866284120000000" Dst="2" />
<file name="pdf.png" server="Y:/" local="128994971340000000" remote="128994971340000000" Dst="2" />
<file name="exec_4-09.jpg" server="Y:/" local="128917214360000000" remote="128917214360000000" Dst="2" />
<file name="vuu.gif" server="Y:/" local="128866334740000000" remote="128866334740000000" Dst="2" />
<file name="RALCMember20014.jpg" server="Y:/" local="130582959709271861" remote="130582959700000000" Dst="2" />
<file name="ralc_banner_bkg.png" server="//sr11cweb03/library/" local="128866283220000000" remote="128866283220000000" Dst="1" />
<file name="ralc_logo.png" server="//sr11cweb03/library/" local="128866284120000000" remote="128866284120000000" Dst="1" />
<file name="pdf.png" server="//sr11cweb03/library/" local="128994971340000000" remote="128994971340000000" Dst="1" />
<file name="ralc_banner_bkg.png" server="//sr11dweb01/library/" local="128866283220000000" remote="128866283220000000" Dst="2" />
<file name="ralc_logo.png" server="//sr11dweb01/library/" local="128866284120000000" remote="128866284120000000" Dst="2" />
<file name="pdf.png" server="//sr11dweb01/library/" local="128994971340000000" remote="128994971340000000" Dst="2" />
<file name="RALCMember20014.jpg" server="//sr11dweb01/library/" local="130582959709271861" remote="130582959700000000" Dst="2" />
<file name="exec_4-09.jpg" server="//sr11dweb01/library/" local="128917214360000000" remote="128917214360000000" Dst="2" />
<file name="vuu.gif" server="//sr11dweb01/library/" local="128866334740000000" remote="128866334740000000" Dst="2" />
</dwsync>